{
  "round": "round34_中段双展示提示卡_正反分段提示修复",
  "baseline_round": "round33_正反展示提示卡补齐与风格统一",
  "goal": "只做 latest_review_pack 的中段局部修复：按图二风格重构《反面展示》《正面展示》两张 9:16 提示卡，不重构整条视频。",
  "visual_plan": {
    "reference_image_status": "已确认：图二参考图可读取，作为粉色樱花柔和展示牌风格参考。",
    "reference_image": {
      "source": "/Users/fan/Desktop/截屏2026-04-25 18.11.07.png",
      "copied_to": "/Users/fan/Documents/视频工厂/dist/20260417_豆包的正确打开方式_vnext/round34_中段双展示提示卡_正反分段提示修复/inputs/图二参考图.png",
      "width": 908,
      "height": 492,
      "status": "已确认：图二参考图可读取，作为粉色樱花柔和展示牌风格参考。"
    },
    "canvas": "720x1280",
    "duration_seconds": 1.6,
    "crossfade_seconds": 0.16,
    "title_layout": "center_large_readable",
    "card_copy": {
      "negative": {
        "title": "《反面展示》",
        "subtitle": "先看旧做法：一句糊话，结果怎么变泛"
      },
      "positive": {
        "title": "《正面展示》",
        "subtitle": "再看工作包后：结果怎么一步步落成"
      }
    },
    "adopted_elements": [
      "图二横图参考",
      "粉色主色",
      "樱花花瓣",
      "小花枝",
      "细线边框",
      "蕾丝花边感",
      "右上角蝴蝶结",
      "圆角展示牌",
      "中心大标题",
      "一句副标题",
      "柔和光感",
      "少量高光粒子"
    ],
    "rejected_elements": [
      "图一橙色网格说明页",
      "横图拉伸",
      "上下加黑边",
      "PPT 大纲页",
      "正反同卡说明",
      "大段正文",
      "bullet list",
      "卡片退后，证据向前"
    ],
    "tokens": {
      "canvas_size": "720x1280",
      "background_top": "#FFE0EF",
      "background_bottom": "#FFF8FC",
      "panel_fill": "#FFF7FB",
      "panel_border": "#EFA3C4",
      "title_fill": "#FFF7FB",
      "title_stroke": "#D86693",
      "subtitle_fill": "#8D4869",
      "shadow": "#C95E8A",
      "petal": "#F6AFC9",
      "branch": "#B97885",
      "highlight": "#FFFFFF"
    }
  },
  "structure": {
    "inserted_positive_prompt_card": true,
    "negative_prompt_card_seconds": 1.6,
    "positive_prompt_card_seconds": 1.6,
    "final_duration_seconds": 55.92
  },
  "prohibited_actions": {
    "ali_api_called": false,
    "host_avatar_regenerated": false,
    "raw_recordings_modified": false,
    "host_shell_rebuilt": false,
    "judgment_card_rebuilt": false,
    "prompt_tail_rebuilt": false,
    "new_explanation_cards_added": false
  },
  "clips": [
    {
      "clip_id": "shot01_intro_host",
      "duration_seconds": 10.424,
      "source": "/Users/fan/Documents/视频工厂/dist/20260417_豆包的正确打开方式_vnext/round31_一镜到底录屏证据链重构/renders/主持壳正式正片_round31_一镜到底录屏证据链重构.mp4 0.000s-10.424s",
      "note": "沿用 round31 / round30 开头主持壳，不重新生成元素娃娃。"
    },
    {
      "clip_id": "shot02_negative_prompt_card",
      "duration_seconds": 1.6,
      "source": "round34 generated 9:16 prompt card",
      "note": "《反面展示》提示卡，图二粉色樱花柔和展示牌风格，副标题仅提示即将进入反面真实录屏，1.6s。"
    },
    {
      "clip_id": "shot03_negative_recording",
      "duration_seconds": 8.4,
      "source": "素材录制/反面/录制于 2026-04-16 22.41.32.mp4 32.000s-40.400s",
      "note": "反面连续录屏，证据链保持不变。"
    },
    {
      "clip_id": "shot04_positive_prompt_card",
      "duration_seconds": 1.6,
      "source": "round34 generated 9:16 prompt card",
      "note": "《正面展示》提示卡，插入于反面录屏和正面录屏之间，副标题仅提示即将进入正面真实录屏，1.6s。"
    },
    {
      "clip_id": "shot05_positive_recording",
      "duration_seconds": 16.0,
      "source": "素材录制/正面/录制于 2026-04-16 23.03.53.mp4 610.000s-626.000s",
      "note": "正面连续录屏，30-32 秒仍落在这一镜头内部。"
    },
    {
      "clip_id": "shot06_result_diff_card",
      "duration_seconds": 1.5,
      "source": "round31 result_diff_card",
      "note": "结果差提示卡保留，不新增解释卡。"
    },
    {
      "clip_id": "shot07_clean_host",
      "duration_seconds": 5.336,
      "source": "/Users/fan/Documents/视频工厂/dist/20260417_豆包的正确打开方式_vnext/round31_一镜到底录屏证据链重构/renders/主持壳正式正片_round31_一镜到底录屏证据链重构.mp4 38.620s-43.956s",
      "note": "回场主持壳沿用干净源片段，不重新生成。"
    },
    {
      "clip_id": "shot08_judgment_card",
      "duration_seconds": 6.08,
      "source": "/Users/fan/Documents/视频工厂/dist/20260417_豆包的正确打开方式_vnext/round31_一镜到底录屏证据链重构/renders/主持壳正式正片_round31_一镜到底录屏证据链重构.mp4 43.956s-50.036s",
      "note": "结尾总结卡保持信息密度不变。"
    },
    {
      "clip_id": "shot09_prompt_tail",
      "duration_seconds": 5.964,
      "source": "/Users/fan/Documents/视频工厂/dist/20260417_豆包的正确打开方式_vnext/round31_一镜到底录屏证据链重构/renders/主持壳正式正片_round31_一镜到底录屏证据链重构.mp4 50.036s-end",
      "note": "Prompt 引用尾卡不承担主叙事和中段证据。"
    }
  ]
}
